git_manager/__init__.py
git_manager/cli.py
git_manager/db.py
git_manager/git_manager.py
git_manager/lolcat.py
git_manager/models.py
gitmanager-0.1.1.dist-info/DESCRIPTION.rst
gitmanager-0.1.1.dist-info/METADATA
gitmanager-0.1.1.dist-info/RECORD
gitmanager-0.1.1.dist-info/WHEEL
gitmanager-0.1.1.dist-info/entry_points.txt
gitmanager-0.1.1.dist-info/metadata.json
gitmanager-0.1.1.dist-info/top_level.txt
