Metadata-Version: 2.0
Name: gitmanager
Version: 0.1.1
Summary: A tool for managing multiple git projects.
Home-page: UNKNOWN
Author: UNKNOWN
Author-email: UNKNOWN
License: UNKNOWN
Platform: UNKNOWN
Classifier: Topic :: Utilities
Classifier: Topic :: Software Development :: Version Control
Classifier: Topic :: Software Development :: Version Control :: Git
Requires-Dist: Click
Requires-Dist: GitPython
Requires-Dist: delegator.py
Requires-Dist: sqlalchemy
Requires-Dist: termcolor
